factors/__init__.py
factors/models.py
factors/settings.py
factors/utils.py
factors/utils_extra.py
factors/data/AEG2011.xlsx
factors/data/AG0409.xlsx
factors/data/AG1262.xlsx
factors/data/AG2014.xlsx
factors/data/COL2003.xlsx
factors/data/GB0005WO.xlsx
factors/data/NN2013.xlsx
factors/data/ZL2007.xlsx
factors/data/ZL2011.xlsx
factors/data/__init__.py
factors/data/tables.csv
factors/examples/__init__.py
factors/tests/__init__.py
factors/tests/conftest.py
factors/tests/test_factors.py
factors/tests/test_new_factors.py
factors/tests/test_utils.py
factors-0.1.1.dist-info/METADATA
factors-0.1.1.dist-info/RECORD
factors-0.1.1.dist-info/WHEEL
factors-0.1.1.dist-info/top_level.txt
