Metadata-Version: 2.1
Name: factors
Version: 0.1.1
Summary: Generates actuarial factors for premium calculations.
Home-page: https://github.com/Oxylo/factors
Author: Pieter Marres
Author-email: pmarres@oxylo.com
License: MIT
Download-URL: https://github.com/Oxylo/factors/archive/0.1.1.tar.gz
Platform: UNKNOWN
Classifier: Development Status :: 3 - Alpha
Classifier: License :: OSI Approved :: MIT License
Classifier: Programming Language :: Python :: 3.5
Classifier: Programming Language :: Python :: 3.6
Requires-Dist: pandas (>=0.23.3)
Requires-Dist: xlrd (>=1.1.0)
Requires-Dist: openpyxl (>=2.5.4)
